aiida_vibroscopy/__init__.py
aiida_vibroscopy/calculations/__init__.py
aiida_vibroscopy/calculations/create_directional_kpoints.py
aiida_vibroscopy/calculations/numerical_derivatives_utils.py
aiida_vibroscopy/calculations/spectra_utils.py
aiida_vibroscopy/calculations/symmetry.py
aiida_vibroscopy/cli/__init__.py
aiida_vibroscopy/cli/utils/__init__.py
aiida_vibroscopy/cli/utils/defaults.py
aiida_vibroscopy/cli/utils/display.py
aiida_vibroscopy/cli/utils/launch.py
aiida_vibroscopy/cli/utils/options.py
aiida_vibroscopy/cli/utils/validate.py
aiida_vibroscopy/cli/workflows/__init__.py
aiida_vibroscopy/cli/workflows/dielectric/__init__.py
aiida_vibroscopy/cli/workflows/dielectric/base.py
aiida_vibroscopy/cli/workflows/phonons/__init__.py
aiida_vibroscopy/cli/workflows/phonons/base.py
aiida_vibroscopy/cli/workflows/phonons/harmonic.py
aiida_vibroscopy/cli/workflows/spectra/__init__.py
aiida_vibroscopy/cli/workflows/spectra/iraman.py
aiida_vibroscopy/common/__init__.py
aiida_vibroscopy/common/constants.py
aiida_vibroscopy/common/properties.py
aiida_vibroscopy/data/__init__.py
aiida_vibroscopy/data/vibro_fp.py
aiida_vibroscopy/data/vibro_lr.py
aiida_vibroscopy/data/vibro_mixin.py
aiida_vibroscopy/utils/__init__.py
aiida_vibroscopy/utils/broadenings.py
aiida_vibroscopy/utils/elfield_cards_functions.py
aiida_vibroscopy/utils/plotting.py
aiida_vibroscopy/utils/spectra.py
aiida_vibroscopy/utils/validation.py
aiida_vibroscopy/utils/integration/__init__.py
aiida_vibroscopy/utils/integration/lebedev.py
aiida_vibroscopy/utils/integration/schemas/__init__.py
aiida_vibroscopy/utils/integration/schemas/lebedev_003.json
aiida_vibroscopy/utils/integration/schemas/lebedev_005.json
aiida_vibroscopy/utils/integration/schemas/lebedev_007.json
aiida_vibroscopy/utils/integration/schemas/lebedev_009.json
aiida_vibroscopy/utils/integration/schemas/lebedev_011.json
aiida_vibroscopy/utils/integration/schemas/lebedev_013.json
aiida_vibroscopy/utils/integration/schemas/lebedev_015.json
aiida_vibroscopy-1.4.0.dist-info/entry_points.txt
aiida_vibroscopy-1.4.0.dist-info/licenses/LICENSE.txt
aiida_vibroscopy-1.4.0.dist-info/WHEEL
aiida_vibroscopy-1.4.0.dist-info/METADATA
aiida_vibroscopy-1.4.0.dist-info/RECORD
