Metadata-Version: 2.4
Name: aiida-vibroscopy
Version: 1.4.0
Summary: AiiDA plugin for vibrational spectoscopy using Quantum ESPRESSO.
Keywords: aiida,workflows
Author-email: Lorenzo Bastonero <bastonero.lorenzo@gmail.com>
Requires-Python: >=3.8
Classifier: Development Status :: 5 - Production/Stable
Classifier: Framework :: AiiDA
Classifier: License :: Other/Proprietary License
Classifier: Operating System :: POSIX :: Linux
Classifier: Operating System :: MacOS :: MacOS X
Classifier: Programming Language :: Python
Classifier: Programming Language :: Python :: 3.8
Classifier: Programming Language :: Python :: 3.9
Classifier: Programming Language :: Python :: 3.10
Classifier: Programming Language :: Python :: 3.11
Classifier: Programming Language :: Python :: 3.12
License-File: LICENSE.txt
Requires-Dist: aiida-core~=2.3
Requires-Dist: aiida-quantumespresso~=4.10
Requires-Dist: aiida-phonopy~=1.3
Requires-Dist: spglib~=2.6
Requires-Dist: phonopy~=2.39
Requires-Dist: myst-nb~=1.0 ; extra == "docs"
Requires-Dist: jupytext>=1.11.2,<1.15.0 ; extra == "docs"
Requires-Dist: sphinx~=6.2.1 ; extra == "docs"
Requires-Dist: sphinx-copybutton~=0.5.2 ; extra == "docs"
Requires-Dist: sphinx-book-theme~=1.0.1 ; extra == "docs"
Requires-Dist: sphinx-click~=4.4.0 ; extra == "docs"
Requires-Dist: sphinx-design~=0.4.1 ; extra == "docs"
Requires-Dist: sphinxcontrib-details-directive~=0.1.0 ; extra == "docs"
Requires-Dist: sphinx-autoapi~=3.0.0 ; extra == "docs"
Requires-Dist: myst-parser~=3.0.0 ; extra == "docs"
Requires-Dist: sphinx-togglebutton ; extra == "docs"
Requires-Dist: pre-commit~=2.17 ; extra == "pre-commit"
Requires-Dist: pylint==2.13.7 ; extra == "pre-commit"
Requires-Dist: pylint-aiida~=0.1.1 ; extra == "pre-commit"
Requires-Dist: toml ; extra == "pre-commit"
Requires-Dist: pgtest~=1.3 ; extra == "tests"
Requires-Dist: pytest~=6.0 ; extra == "tests"
Requires-Dist: coverage[toml] ; extra == "tests"
Requires-Dist: pytest-cov ; extra == "tests"
Requires-Dist: pytest-regressions~=2.3 ; extra == "tests"
Requires-Dist: pytest-timeout ; extra == "tests"
Project-URL: Source, https://github.com/bastonero/aiida-vibroscopy
Provides-Extra: docs
Provides-Extra: pre-commit
Provides-Extra: tests
